python_picnic_api2/__init__.py
python_picnic_api2/client.py
python_picnic_api2/helper.py
python_picnic_api2/session.py
python_picnic_api2-1.3.2.dist-info/METADATA
python_picnic_api2-1.3.2.dist-info/WHEEL
python_picnic_api2-1.3.2.dist-info/licenses/LICENSE.md
python_picnic_api2-1.3.2.dist-info/RECORD
