Metadata-Version: 2.4
Name: python-picnic-api2
Version: 1.3.2
Project-URL: homepage, https://github.com/codesalatdev/python-picnic-api
Project-URL: repository, https://github.com/codesalatdev/python-picnic-api
Author-email: Mike Brink <mjh.brink@icloud.com>, CodeSalat <pypi@codesalat.dev>
Maintainer-email: CodeSalat <pypi@codesalat.dev>
License: Apache-2.0
License-File: LICENSE.md
Requires-Python: >=3.11
Requires-Dist: requests>=2.24.0
Requires-Dist: typing-extensions>=4.12.2
